audinter/__init__.py
audinter/metrics.py
audinter-0.1.0.dist-info/LICENSE
audinter-0.1.0.dist-info/METADATA
audinter-0.1.0.dist-info/WHEEL
audinter-0.1.0.dist-info/RECORD
